ZscoreToolV1/__init__.py
ZscoreToolV1/createnetwork.py
ZscoreToolV1/mapnetwork.py
ZscoreToolV1-0.0.40.dist-info/METADATA
ZscoreToolV1-0.0.40.dist-info/WHEEL
ZscoreToolV1-0.0.40.dist-info/top_level.txt
ZscoreToolV1-0.0.40.dist-info/RECORD
