Metadata-Version: 2.1
Name: ZscoreToolV1
Version: 0.0.40
Summary: Test python package
Author: Emma Gerrits
Author-email: emma.gerrits@ki.se
Keywords: python,first package
Classifier: Development Status :: 3 - Alpha
Classifier: Intended Audience :: Education
Classifier: Programming Language :: Python :: 3
Classifier: Operating System :: MacOS :: MacOS X
Classifier: Operating System :: Microsoft :: Windows
Classifier: Operating System :: POSIX :: Linux
Requires-Dist: numpy
Requires-Dist: pandas
Requires-Dist: scanpy
Requires-Dist: umap
Requires-Dist: scipy
Requires-Dist: tqdm
Requires-Dist: adjustText
Requires-Dist: scikit-learn
Requires-Dist: matplotlib
Requires-Dist: tifffile
Requires-Dist: Pillow
